cowfish/__init__.py
cowfish/firehose.py
cowfish/kinesis.py
cowfish/pool.py
cowfish/sqs.py
cowfish/sqsprocesser.py
cowfish/utils.py
cowfish/worker.py
cowfish-0.3.1.dist-info/LICENSE
cowfish-0.3.1.dist-info/METADATA
cowfish-0.3.1.dist-info/WHEEL
cowfish-0.3.1.dist-info/entry_points.txt
cowfish-0.3.1.dist-info/top_level.txt
cowfish-0.3.1.dist-info/RECORD
