Metadata-Version: 2.1
Name: cowfish
Version: 0.3.1
Summary: A useful asynchronous library that is built on top of aiobotocore
Home-page: https://github.com/guyingbo/cowfish
Author: Yingbo Gu
Author-email: tensiongyb@gmail.com
Maintainer: Yingbo Gu
Maintainer-email: tensiongyb@gmail.com
License: MIT
Platform: UNKNOWN
Classifier: License :: OSI Approved :: MIT License
Classifier: Framework :: AsyncIO
Classifier: Intended Audience :: Developers
Classifier: Programming Language :: Python :: 3.6
Classifier: Programming Language :: Python :: 3.7
Classifier: Programming Language :: Python :: 3.8
Requires-Python: >=3.6
Requires-Dist: aiobotocore (>=1.0.0)
